srdatasets/__init__.py
srdatasets/__main__.py
srdatasets/dataloader.py
srdatasets/dataloader_pytorch.py
srdatasets/download.py
srdatasets/process.py
srdatasets/utils.py
srdatasets/datasets/__init__.py
srdatasets/datasets/amazon.py
srdatasets/datasets/citeulike.py
srdatasets/datasets/dataset.py
srdatasets/datasets/foursquare.py
srdatasets/datasets/gowalla.py
srdatasets/datasets/lastfm1k.py
srdatasets/datasets/movielens20m.py
srdatasets/datasets/retailrocket.py
srdatasets/datasets/tafeng.py
srdatasets/datasets/taobao.py
srdatasets/datasets/tmall.py
srdatasets/datasets/utils.py
srdatasets/datasets/yelp.py
srdatasets-0.1.4.dist-info/LICENSE
srdatasets-0.1.4.dist-info/METADATA
srdatasets-0.1.4.dist-info/WHEEL
srdatasets-0.1.4.dist-info/entry_points.txt
srdatasets-0.1.4.dist-info/top_level.txt
srdatasets-0.1.4.dist-info/RECORD
