Metadata-Version: 2.1
Name: srdatasets
Version: 0.1.4
Summary: A collection of research ready datasets for sequential recommendation
Home-page: https://github.com/guocheng2018/sequential-recommendation-datasets
Author: Cheng Guo
Author-email: guocheng672@gmail.com
License: UNKNOWN
Platform: UNKNOWN
Classifier: Development Status :: 4 - Beta
Classifier: Intended Audience :: Developers
Classifier: Intended Audience :: Science/Research
Classifier: License :: OSI Approved :: Apache Software License
Requires-Python: >=3.6
Requires-Dist: pandas (>=0.25.0)
Requires-Dist: tqdm (>=4.33.0)
Requires-Dist: tabulate (>=0.8.5)
Requires-Dist: numpy (>=1.16.4)
